py_brainage/__init__.py
py_brainage/trees.py
py_brainage-0.0.22.dist-info/LICENSE
py_brainage-0.0.22.dist-info/METADATA
py_brainage-0.0.22.dist-info/WHEEL
py_brainage-0.0.22.dist-info/top_level.txt
py_brainage-0.0.22.dist-info/RECORD
