Metadata-Version: 2.1
Name: py-brainage
Version: 0.0.22
Summary: Description of your package
Home-page: UNKNOWN
License: UNKNOWN
Platform: UNKNOWN
License-File: LICENSE
Requires-Dist: numpy
Requires-Dist: pandas
Requires-Dist: scikit-learn
